magpai/__init__.py
magpai/version.py
tests/__init__.py
tests/tests_helper.py
tests/helpers/__init__.py
tests/helpers/my_helper.py
tests/unit/__init__.py
tests/unit/test_workflows.py
magpai-1.1.0.dist-info/LICENSE
magpai-1.1.0.dist-info/METADATA
magpai-1.1.0.dist-info/WHEEL
magpai-1.1.0.dist-info/top_level.txt
magpai-1.1.0.dist-info/RECORD
